rocketlogger/__init__.py
rocketlogger/calibration.py
rocketlogger/data.py
rocketlogger-2.1.3.dist-info/licenses/LICENSE
rocketlogger-2.1.3.dist-info/METADATA
rocketlogger-2.1.3.dist-info/WHEEL
rocketlogger-2.1.3.dist-info/top_level.txt
rocketlogger-2.1.3.dist-info/RECORD
