Metadata-Version: 2.4
Name: rocketlogger
Version: 2.1.3
Summary: RocketLogger Python Support
Home-page: https://github.com/ETHZ-TEC/RocketLogger#readme
Author: ETH Zurich, Computer Engineering Group
License: BSD 3-Clause
Project-URL: Documentation, https://github.com/ETHZ-TEC/RocketLogger/wiki/python
Project-URL: Source, https://github.com/ETHZ-TEC/RocketLogger
Project-URL: Tracker, https://github.com/ETHZ-TEC/RocketLogger/issues
Keywords: rocketlogger,data analysis,calibration
Classifier: Development Status :: 5 - Production/Stable
Classifier: Intended Audience :: Information Technology
Classifier: Intended Audience :: Science/Research
Classifier: Topic :: Scientific/Engineering :: Information Analysis
Classifier: Programming Language :: Python :: 3
Classifier: Programming Language :: Python :: 3.6
Classifier: Programming Language :: Python :: 3.7
Classifier: Programming Language :: Python :: 3.8
Classifier: Programming Language :: Python :: 3.9
Classifier: Programming Language :: Python :: 3.10
Classifier: Programming Language :: Python :: 3.11
Classifier: Programming Language :: Python :: 3.12
Classifier: Programming Language :: Python :: 3.13
Classifier: Programming Language :: Python :: 3.14
Classifier: Programming Language :: Python :: 3 :: Only
Classifier: License :: OSI Approved :: BSD License
Classifier: Operating System :: OS Independent
Requires-Python: >=3.6, <4
License-File: LICENSE
Requires-Dist: numpy<2.4,>=1.13
Provides-Extra: dataframe
Requires-Dist: pandas; extra == "dataframe"
Provides-Extra: plot
Requires-Dist: matplotlib; extra == "plot"
Provides-Extra: dev
Requires-Dist: black; extra == "dev"
Requires-Dist: sphinx; extra == "dev"
Provides-Extra: test
Requires-Dist: pytest; extra == "test"
Requires-Dist: pytest-cov; extra == "test"
Requires-Dist: tox; extra == "test"
Dynamic: author
Dynamic: classifier
Dynamic: description
Dynamic: description-content-type
Dynamic: home-page
Dynamic: keywords
Dynamic: license
Dynamic: license-file
Dynamic: project-url
Dynamic: provides-extra
Dynamic: requires-dist
Dynamic: requires-python
Dynamic: summary
